{
  "name": "interact_with_process",
  "description": "\n                        Send input to a running process and automatically receive the response.\n                        \n                        CRITICAL: THIS IS THE PRIMARY TOOL FOR ALL LOCAL FILE ANALYSIS\n                        For ANY local file analysis (CSV, JSON, data processing), ALWAYS use this instead of the analysis tool.\n                        The analysis tool CANNOT access local files and WILL FAIL - use processes for ALL file-based work.\n                        \n                        FILE ANALYSIS PRIORITY ORDER (MANDATORY):\n                        1. ALWAYS FIRST: Use this tool (start_process + interact_with_process) for local data analysis\n                        2. ALTERNATIVE: Use command-line tools (cut, awk, grep) for quick processing  \n                        3. NEVER EVER: Use analysis tool for local file access (IT WILL FAIL)\n                        \n                        REQUIRED INTERACTIVE WORKFLOW FOR FILE ANALYSIS:\n                        1. Start REPL: start_process(\"python3 -i\")\n                        2. Load libraries: interact_with_process(pid, \"import pandas as pd, numpy as np\")\n                        3. Read file: interact_with_process(pid, \"df = pd.read_csv('/absolute/path/file.csv')\")\n                        4. Analyze: interact_with_process(pid, \"print(df.describe())\")\n                        5. Continue: interact_with_process(pid, \"df.groupby('column').size()\")\n                        \n                        BINARY FILE PROCESSING WORKFLOWS:\n                        Use appropriate Python libraries (PyPDF2, pandas, docx2txt, etc.) or command-line tools for binary file analysis.\n                        \n                        SMART DETECTION:\n                        - Automatically waits for REPL prompt (>>>, >, etc.)\n                        - Detects errors and completion states\n                        - Early exit prevents timeout delays\n                        - Clean output formatting (removes prompts)\n                        \n                        SUPPORTED REPLs:\n                        - Python: python3 -i (RECOMMENDED for data analysis)\n                        - Node.js: node -i\n                        - R: R\n                        - Julia: julia\n                        - Shell: bash, zsh\n                        - Database: mysql, postgres\n                        \n                        PARAMETERS:\n                        - pid: Process ID from start_process\n                        - input: Code/command to execute\n                        - timeout_ms: Max wait (default: 8000ms)\n                        - wait_for_prompt: Auto-wait for response (default: true)\n                        - verbose_timing: Enable detailed performance telemetry (default: false)\n\n                        Returns execution result with status indicators.\n\n                        PERFORMANCE DEBUGGING (verbose_timing parameter):\n                        Set verbose_timing: true to get detailed timing information including:\n                        - Exit reason (early_exit_quick_pattern, early_exit_periodic_check, process_finished, timeout, no_wait)\n                        - Total duration and time to first output\n                        - Complete timeline of all output events with timestamps\n                        - Which detection mechanism triggered early exit\n                        Use this to identify slow interactions and optimize detection patterns.\n\n                        ALWAYS USE FOR: CSV analysis, JSON processing, file statistics, data visualization prep, ANY local file work\n                        NEVER USE ANALYSIS TOOL FOR: Local file access (it cannot read files from disk and WILL FAIL)\n\n                        This command can be referenced as \"DC: ...\" or \"use Desktop Commander to ...\" in your instructions.",
  "inputSchema": {
    "type": "object",
    "properties": {
      "pid": {
        "type": "number"
      },
      "input": {
        "type": "string"
      },
      "timeout_ms": {
        "type": "number"
      },
      "wait_for_prompt": {
        "type": "boolean"
      },
      "verbose_timing": {
        "type": "boolean"
      }
    },
    "required": [
      "pid",
      "input"
    ],
    "additionalProperties": false,
    "$schema": "http://json-schema.org/draft-07/schema#"
  }
}